libsql/db/backends/libsql/__init__.py
libsql/db/backends/libsql/base.py
libsql/db/backends/libsql/client.py
libsql/db/backends/libsql/creation.py
libsql/db/backends/libsql/features.py
libsql/db/backends/libsql/introspection.py
libsql/db/backends/libsql/operations.py
libsql/db/backends/libsql/schema.py
libsql/db/backends/sqlite3/__init__.py
libsql/db/backends/sqlite3/base.py
libsql/db/backends/sqlite3/client.py
libsql/db/backends/sqlite3/creation.py
libsql/db/backends/sqlite3/features.py
libsql/db/backends/sqlite3/introspection.py
libsql/db/backends/sqlite3/operations.py
libsql/db/backends/sqlite3/schema.py
django_libsql-0.1.3.dist-info/METADATA
django_libsql-0.1.3.dist-info/WHEEL
django_libsql-0.1.3.dist-info/top_level.txt
django_libsql-0.1.3.dist-info/RECORD
