Metadata-Version: 2.1
Name: django-libsql
Version: 0.1.3
Summary: A Django integration for libSQL / turso database
Home-page: https://github.com/aaronkazah/django-libsql
Author: Aaron Kazah
Classifier: Development Status :: 3 - Alpha
Classifier: Intended Audience :: Developers
Classifier: License :: OSI Approved :: MIT License
Classifier: Operating System :: OS Independent
Classifier: Programming Language :: Python :: 3
Classifier: Programming Language :: Python :: 3.8
Classifier: Programming Language :: Python :: 3.9
Classifier: Programming Language :: Python :: 3.10
Classifier: Programming Language :: Python :: 3.11
Classifier: Framework :: Django
Requires-Python: >=3
Requires-Dist: Django>=2.0
Requires-Dist: libsql-client
